MANIFEST.in
README.md
lan-ls
requirements.txt
setup.py
version.py
lan_ls.egg-info/PKG-INFO
lan_ls.egg-info/SOURCES.txt
lan_ls.egg-info/dependency_links.txt
lan_ls.egg-info/top_level.txt