Metadata-Version: 2.1
Name: lan-ls
Version: 0.20200819.1
Summary: List devices on your LAN
Home-page: https://github.com/davidvilla/lan-ls
Author: David Villa Alises
Author-email: David.Villa@gmail.com
License: GPL v2 or later
Platform: UNKNOWN
Classifier: Programming Language :: Python :: 3
